{
  "game_id": "game-1781696264793838000-58351463",
  "result": "black_win",
  "game": {
    "id": "game-1781696264793838000-58351463",
    "mode": "ai_vs_ai",
    "type": "chess",
    "config": {
      "humanColor": "white",
      "aiGameCount": 1,
      "startFen": "",
      "aiProfile": "intermediate"
    },
    "result": "black_win",
    "outcome": {
      "status": "resigned",
      "winner": "black",
      "loser": "white",
      "legalMoves": 0,
      "message": "White flagged. Black wins."
    },
    "createdAt": "2026-06-17T11:37:44Z",
    "updatedAt": "2026-06-17T11:39:48Z"
  },
  "history": [],
  "move_analysis": null,
  "exported_at": "2026-06-17T11:39:48Z"
}