{
  "archived_at": "2026-06-17T14:57:01Z",
  "game_id": "game-1781708220272407000-0903ef4f",
  "history_detailed": [
    {
      "side": "White",
      "pieceKind": "pawn",
      "to": "e4",
      "command": "e2e4",
      "isCapture": false
    },
    {
      "side": "Black",
      "pieceKind": "pawn",
      "to": "d5",
      "command": "d7d5",
      "isCapture": false
    },
    {
      "side": "White",
      "pieceKind": "pawn",
      "to": "d5",
      "command": "e4d5",
      "isCapture": true,
      "capturedPieceKind": "pawn"
    },
    {
      "side": "Black",
      "pieceKind": "pawn",
      "to": "c6",
      "command": "c7c6",
      "isCapture": false
    },
    {
      "side": "White",
      "pieceKind": "pawn",
      "to": "c4",
      "command": "c2c4",
      "isCapture": false
    },
    {
      "side": "Black",
      "pieceKind": "pawn",
      "to": "d5",
      "command": "c6d5",
      "isCapture": true,
      "capturedPieceKind": "pawn"
    },
    {
      "side": "White",
      "pieceKind": "knight",
      "to": "f3",
      "command": "g1f3",
      "isCapture": false
    },
    {
      "side": "Black",
      "pieceKind": "pawn",
      "to": "d4",
      "command": "d5d4",
      "isCapture": false
    },
    {
      "side": "White",
      "pieceKind": "pawn",
      "to": "h3",
      "command": "h2h3",
      "isCapture": false
    },
    {
      "side": "Black",
      "pieceKind": "knight",
      "to": "c6",
      "command": "b8c6",
      "isCapture": false
    },
    {
      "side": "White",
      "pieceKind": "pawn",
      "to": "b4",
      "command": "b2b4",
      "isCapture": false
    },
    {
      "side": "Black",
      "pieceKind": "pawn",
      "to": "d3",
      "command": "d4d3",
      "isCapture": false
    },
    {
      "side": "White",
      "pieceKind": "bishop",
      "to": "a3",
      "command": "c1a3",
      "isCapture": false
    },
    {
      "side": "Black",
      "pieceKind": "pawn",
      "to": "e5",
      "command": "e7e5",
      "isCapture": false
    },
    {
      "side": "White",
      "pieceKind": "pawn",
      "to": "b5",
      "command": "b4b5",
      "isCapture": false
    },
    {
      "side": "Black",
      "pieceKind": "pawn",
      "to": "e4",
      "command": "e5e4",
      "isCapture": false
    },
    {
      "side": "White",
      "pieceKind": "pawn",
      "to": "c6",
      "command": "b5c6",
      "isCapture": true,
      "capturedPieceKind": "knight"
    },
    {
      "side": "Black",
      "pieceKind": "bishop",
      "to": "a3",
      "command": "f8a3",
      "isCapture": true,
      "capturedPieceKind": "bishop"
    },
    {
      "side": "White",
      "pieceKind": "pawn",
      "to": "b7",
      "command": "c6b7",
      "isCapture": true,
      "capturedPieceKind": "pawn"
    },
    {
      "side": "Black",
      "pieceKind": "bishop",
      "to": "b7",
      "command": "c8b7",
      "isCapture": true,
      "capturedPieceKind": "pawn"
    },
    {
      "side": "White",
      "pieceKind": "knight",
      "to": "e5",
      "command": "f3e5",
      "isCapture": false
    },
    {
      "side": "Black",
      "pieceKind": "king",
      "to": "f8",
      "command": "e8f8",
      "isCapture": false
    },
    {
      "side": "White",
      "pieceKind": "knight",
      "to": "f7",
      "command": "e5f7",
      "isCapture": true,
      "capturedPieceKind": "pawn"
    },
    {
      "side": "Black",
      "pieceKind": "king",
      "to": "f7",
      "command": "f8f7",
      "isCapture": true,
      "capturedPieceKind": "knight"
    },
    {
      "side": "White",
      "pieceKind": "knight",
      "to": "a3",
      "command": "b1a3",
      "isCapture": true,
      "capturedPieceKind": "bishop"
    },
    {
      "side": "Black",
      "pieceKind": "knight",
      "to": "f6",
      "command": "g8f6",
      "isCapture": false
    },
    {
      "side": "White",
      "pieceKind": "rook",
      "to": "b1",
      "command": "a1b1",
      "isCapture": false
    },
    {
      "side": "Black",
      "pieceKind": "bishop",
      "to": "c6",
      "command": "b7c6",
      "isCapture": false
    },
    {
      "side": "White",
      "pieceKind": "queen",
      "to": "b3",
      "command": "d1b3",
      "isCapture": false
    },
    {
      "side": "Black",
      "pieceKind": "pawn",
      "to": "e3",
      "command": "e4e3",
      "isCapture": false
    },
    {
      "side": "White",
      "pieceKind": "bishop",
      "to": "d3",
      "command": "f1d3",
      "isCapture": true,
      "capturedPieceKind": "pawn"
    },
    {
      "side": "Black",
      "pieceKind": "pawn",
      "to": "f2",
      "command": "e3f2",
      "isCapture": true,
      "capturedPieceKind": "pawn"
    },
    {
      "side": "White",
      "pieceKind": "king",
      "to": "f1",
      "command": "e1f1",
      "isCapture": false
    },
    {
      "side": "Black",
      "pieceKind": "rook",
      "to": "e8",
      "command": "h8e8",
      "isCapture": false
    },
    {
      "side": "White",
      "pieceKind": "queen",
      "to": "c3",
      "command": "b3c3",
      "isCapture": false
    },
    {
      "side": "Black",
      "pieceKind": "knight",
      "to": "h5",
      "command": "f6h5",
      "isCapture": false
    },
    {
      "side": "White",
      "pieceKind": "rook",
      "to": "b5",
      "command": "b1b5",
      "isCapture": false
    },
    {
      "side": "Black",
      "pieceKind": "knight",
      "to": "g3",
      "command": "h5g3",
      "isCapture": false
    },
    {
      "side": "White",
      "pieceKind": "king",
      "to": "f2",
      "command": "f1f2",
      "isCapture": true,
      "capturedPieceKind": "pawn"
    },
    {
      "side": "Black",
      "pieceKind": "knight",
      "to": "h1",
      "command": "g3h1",
      "isCapture": true,
      "capturedPieceKind": "rook"
    },
    {
      "side": "White",
      "pieceKind": "king",
      "to": "g1",
      "command": "f2g1",
      "isCapture": false
    },
    {
      "side": "Black",
      "pieceKind": "rook",
      "to": "e1",
      "command": "e8e1",
      "isCapture": false
    },
    {
      "side": "White",
      "pieceKind": "bishop",
      "to": "f1",
      "command": "d3f1",
      "isCapture": false
    },
    {
      "side": "Black",
      "pieceKind": "king",
      "to": "g8",
      "command": "f7g8",
      "isCapture": false
    },
    {
      "side": "White",
      "pieceKind": "rook",
      "to": "f5",
      "command": "b5f5",
      "isCapture": false
    },
    {
      "side": "Black",
      "pieceKind": "queen",
      "to": "c7",
      "command": "d8c7",
      "isCapture": false
    },
    {
      "side": "White",
      "pieceKind": "pawn",
      "to": "c5",
      "command": "c4c5",
      "isCapture": false
    },
    {
      "side": "Black",
      "pieceKind": "knight",
      "to": "g3",
      "command": "h1g3",
      "isCapture": false
    },
    {
      "side": "White",
      "pieceKind": "rook",
      "to": "f2",
      "command": "f5f2",
      "isCapture": false
    },
    {
      "side": "Black",
      "pieceKind": "king",
      "to": "h8",
      "command": "g8h8",
      "isCapture": false
    },
    {
      "side": "White",
      "pieceKind": "queen",
      "to": "d3",
      "command": "c3d3",
      "isCapture": false
    },
    {
      "side": "Black",
      "pieceKind": "knight",
      "to": "e4",
      "command": "g3e4",
      "isCapture": false
    },
    {
      "side": "White",
      "pieceKind": "rook",
      "to": "e2",
      "command": "f2e2",
      "isCapture": false
    },
    {
      "side": "Black",
      "pieceKind": "rook",
      "to": "d1",
      "command": "e1d1",
      "isCapture": false
    },
    {
      "side": "White",
      "pieceKind": "knight",
      "to": "c2",
      "command": "a3c2",
      "isCapture": false
    },
    {
      "side": "Black",
      "pieceKind": "rook",
      "to": "f1",
      "command": "d1f1",
      "isCapture": true,
      "capturedPieceKind": "bishop"
    },
    {
      "side": "White",
      "pieceKind": "king",
      "to": "f1",
      "command": "g1f1",
      "isCapture": true,
      "capturedPieceKind": "rook"
    },
    {
      "side": "Black",
      "pieceKind": "queen",
      "to": "h2",
      "command": "c7h2",
      "isCapture": false
    },
    {
      "side": "White",
      "pieceKind": "queen",
      "to": "e4",
      "command": "d3e4",
      "isCapture": true,
      "capturedPieceKind": "knight"
    },
    {
      "side": "Black",
      "pieceKind": "bishop",
      "to": "e4",
      "command": "c6e4",
      "isCapture": true,
      "capturedPieceKind": "queen"
    },
    {
      "side": "White",
      "pieceKind": "rook",
      "to": "e4",
      "command": "e2e4",
      "isCapture": true,
      "capturedPieceKind": "bishop"
    },
    {
      "side": "Black",
      "pieceKind": "rook",
      "to": "f8",
      "command": "a8f8",
      "isCapture": false
    },
    {
      "side": "White",
      "pieceKind": "king",
      "to": "e2",
      "command": "f1e2",
      "isCapture": false
    },
    {
      "side": "Black",
      "pieceKind": "queen",
      "to": "g2",
      "command": "h2g2",
      "isCapture": true,
      "capturedPieceKind": "pawn"
    },
    {
      "side": "White",
      "pieceKind": "king",
      "to": "d3",
      "command": "e2d3",
      "isCapture": false
    },
    {
      "side": "Black",
      "pieceKind": "queen",
      "to": "g6",
      "command": "g2g6",
      "isCapture": false
    },
    {
      "side": "White",
      "pieceKind": "pawn",
      "to": "a3",
      "command": "a2a3",
      "isCapture": false
    },
    {
      "side": "Black",
      "pieceKind": "rook",
      "to": "e8",
      "command": "f8e8",
      "isCapture": false
    },
    {
      "side": "White",
      "pieceKind": "king",
      "to": "c3",
      "command": "d3c3",
      "isCapture": false
    },
    {
      "side": "Black",
      "pieceKind": "queen",
      "to": "f6",
      "command": "g6f6",
      "isCapture": false
    },
    {
      "side": "White",
      "pieceKind": "rook",
      "to": "d4",
      "command": "e4d4",
      "isCapture": false
    },
    {
      "side": "Black",
      "pieceKind": "rook",
      "to": "d8",
      "command": "e8d8",
      "isCapture": false
    },
    {
      "side": "White",
      "pieceKind": "pawn",
      "to": "d3",
      "command": "d2d3",
      "isCapture": false
    },
    {
      "side": "Black",
      "pieceKind": "pawn",
      "to": "h5",
      "command": "h7h5",
      "isCapture": false
    },
    {
      "side": "White",
      "pieceKind": "pawn",
      "to": "a4",
      "command": "a3a4",
      "isCapture": false
    },
    {
      "side": "Black",
      "pieceKind": "rook",
      "to": "b8",
      "command": "d8b8",
      "isCapture": false
    },
    {
      "side": "White",
      "pieceKind": "pawn",
      "to": "c6",
      "command": "c5c6",
      "isCapture": false
    },
    {
      "side": "Black",
      "pieceKind": "rook",
      "to": "d8",
      "command": "b8d8",
      "isCapture": false
    },
    {
      "side": "White",
      "pieceKind": "king",
      "to": "c4",
      "command": "c3c4",
      "isCapture": false
    },
    {
      "side": "Black",
      "pieceKind": "queen",
      "to": "c6",
      "command": "f6c6",
      "isCapture": true,
      "capturedPieceKind": "pawn"
    },
    {
      "side": "White",
      "pieceKind": "king",
      "to": "b3",
      "command": "c4b3",
      "isCapture": false
    },
    {
      "side": "Black",
      "pieceKind": "rook",
      "to": "d4",
      "command": "d8d4",
      "isCapture": true,
      "capturedPieceKind": "rook"
    },
    {
      "side": "White",
      "pieceKind": "knight",
      "to": "d4",
      "command": "c2d4",
      "isCapture": true,
      "capturedPieceKind": "rook"
    },
    {
      "side": "Black",
      "pieceKind": "queen",
      "to": "d5",
      "command": "c6d5",
      "isCapture": false
    },
    {
      "side": "White",
      "pieceKind": "king",
      "to": "c2",
      "command": "b3c2",
      "isCapture": false
    },
    {
      "side": "Black",
      "pieceKind": "pawn",
      "to": "a6",
      "command": "a7a6",
      "isCapture": false
    },
    {
      "side": "White",
      "pieceKind": "knight",
      "to": "b3",
      "command": "d4b3",
      "isCapture": false
    },
    {
      "side": "Black",
      "pieceKind": "king",
      "to": "g8",
      "command": "h8g8",
      "isCapture": false
    },
    {
      "side": "White",
      "pieceKind": "knight",
      "to": "c1",
      "command": "b3c1",
      "isCapture": false
    },
    {
      "side": "Black",
      "pieceKind": "king",
      "to": "f7",
      "command": "g8f7",
      "isCapture": false
    },
    {
      "side": "White",
      "pieceKind": "pawn",
      "to": "d4",
      "command": "d3d4",
      "isCapture": false
    },
    {
      "side": "Black",
      "pieceKind": "queen",
      "to": "g2",
      "command": "d5g2",
      "isCapture": false
    },
    {
      "side": "White",
      "pieceKind": "king",
      "to": "d1",
      "command": "c2d1",
      "isCapture": false
    },
    {
      "side": "Black",
      "pieceKind": "queen",
      "to": "f3",
      "command": "g2f3",
      "isCapture": false
    },
    {
      "side": "White",
      "pieceKind": "king",
      "to": "c2",
      "command": "d1c2",
      "isCapture": false
    },
    {
      "side": "Black",
      "pieceKind": "queen",
      "to": "e3",
      "command": "f3e3",
      "isCapture": false
    },
    {
      "side": "White",
      "pieceKind": "pawn",
      "to": "a5",
      "command": "a4a5",
      "isCapture": false
    },
    {
      "side": "Black",
      "pieceKind": "pawn",
      "to": "g6",
      "command": "g7g6",
      "isCapture": false
    },
    {
      "side": "White",
      "pieceKind": "pawn",
      "to": "h4",
      "command": "h3h4",
      "isCapture": false
    },
    {
      "side": "Black",
      "pieceKind": "king",
      "to": "e6",
      "command": "f7e6",
      "isCapture": false
    },
    {
      "side": "White",
      "pieceKind": "knight",
      "to": "b3",
      "command": "c1b3",
      "isCapture": false
    },
    {
      "side": "Black",
      "pieceKind": "king",
      "to": "f5",
      "command": "e6f5",
      "isCapture": false
    },
    {
      "side": "White",
      "pieceKind": "knight",
      "to": "c1",
      "command": "b3c1",
      "isCapture": false
    },
    {
      "side": "Black",
      "pieceKind": "queen",
      "to": "e4",
      "command": "e3e4",
      "isCapture": false
    },
    {
      "side": "White",
      "pieceKind": "king",
      "to": "c3",
      "command": "c2c3",
      "isCapture": false
    },
    {
      "side": "Black",
      "pieceKind": "queen",
      "to": "e1",
      "command": "e4e1",
      "isCapture": false
    },
    {
      "side": "White",
      "pieceKind": "king",
      "to": "d3",
      "command": "c3d3",
      "isCapture": false
    },
    {
      "side": "Black",
      "pieceKind": "queen",
      "to": "c1",
      "command": "e1c1",
      "isCapture": true,
      "capturedPieceKind": "knight"
    },
    {
      "side": "White",
      "pieceKind": "king",
      "to": "e2",
      "command": "d3e2",
      "isCapture": false
    },
    {
      "side": "Black",
      "pieceKind": "queen",
      "to": "a3",
      "command": "c1a3",
      "isCapture": false
    },
    {
      "side": "White",
      "pieceKind": "king",
      "to": "f1",
      "command": "e2f1",
      "isCapture": false
    },
    {
      "side": "Black",
      "pieceKind": "queen",
      "to": "a5",
      "command": "a3a5",
      "isCapture": true,
      "capturedPieceKind": "pawn"
    },
    {
      "side": "White",
      "pieceKind": "pawn",
      "to": "d5",
      "command": "d4d5",
      "isCapture": false
    },
    {
      "side": "Black",
      "pieceKind": "king",
      "to": "g4",
      "command": "f5g4",
      "isCapture": false
    },
    {
      "side": "White",
      "pieceKind": "pawn",
      "to": "d6",
      "command": "d5d6",
      "isCapture": false
    },
    {
      "side": "Black",
      "pieceKind": "queen",
      "to": "d2",
      "command": "a5d2",
      "isCapture": false
    },
    {
      "side": "White",
      "pieceKind": "king",
      "to": "g1",
      "command": "f1g1",
      "isCapture": false
    },
    {
      "side": "Black",
      "pieceKind": "king",
      "to": "f3",
      "command": "g4f3",
      "isCapture": false
    },
    {
      "side": "White",
      "pieceKind": "king",
      "to": "h1",
      "command": "g1h1",
      "isCapture": false
    },
    {
      "side": "Black",
      "pieceKind": "queen",
      "to": "d6",
      "command": "d2d6",
      "isCapture": true,
      "capturedPieceKind": "pawn"
    },
    {
      "side": "White",
      "pieceKind": "king",
      "to": "g1",
      "command": "h1g1",
      "isCapture": false
    },
    {
      "side": "Black",
      "pieceKind": "queen",
      "to": "g3",
      "command": "d6g3",
      "isCapture": false
    },
    {
      "side": "White",
      "pieceKind": "king",
      "to": "h1",
      "command": "g1h1",
      "isCapture": false
    },
    {
      "side": "Black",
      "pieceKind": "queen",
      "to": "h3",
      "command": "g3h3",
      "isCapture": false
    },
    {
      "side": "White",
      "pieceKind": "king",
      "to": "g1",
      "command": "h1g1",
      "isCapture": false
    },
    {
      "side": "Black",
      "pieceKind": "queen",
      "to": "h4",
      "command": "h3h4",
      "isCapture": true,
      "capturedPieceKind": "pawn"
    },
    {
      "side": "White",
      "pieceKind": "king",
      "to": "f1",
      "command": "g1f1",
      "isCapture": false
    },
    {
      "side": "Black",
      "pieceKind": "queen",
      "to": "g5",
      "command": "h4g5",
      "isCapture": false
    },
    {
      "side": "White",
      "pieceKind": "king",
      "to": "e1",
      "command": "f1e1",
      "isCapture": false
    },
    {
      "side": "Black",
      "pieceKind": "queen",
      "to": "c1",
      "command": "g5c1",
      "isCapture": false
    }
  ],
  "mode": "ai_vs_ai",
  "move_count": 130,
  "profile": "intermediate",
  "result": "black_win",
  "winner": "black"
}