{
  "archived_at": "2026-06-17T10:22:51Z",
  "game_id": "game-1781691770176809000-7d749bee",
  "history_detailed": [
    {
      "side": "White",
      "pieceKind": "pawn",
      "to": "d4",
      "command": "d2d4",
      "isCapture": false
    },
    {
      "side": "Black",
      "pieceKind": "pawn",
      "to": "d5",
      "command": "d7d5",
      "isCapture": false
    },
    {
      "side": "White",
      "pieceKind": "knight",
      "to": "f3",
      "command": "g1f3",
      "isCapture": false
    },
    {
      "side": "Black",
      "pieceKind": "pawn",
      "to": "c6",
      "command": "c7c6",
      "isCapture": false
    },
    {
      "side": "White",
      "pieceKind": "knight",
      "to": "c3",
      "command": "b1c3",
      "isCapture": false
    },
    {
      "side": "Black",
      "pieceKind": "pawn",
      "to": "e6",
      "command": "e7e6",
      "isCapture": false
    },
    {
      "side": "White",
      "pieceKind": "pawn",
      "to": "e4",
      "command": "e2e4",
      "isCapture": false
    },
    {
      "side": "Black",
      "pieceKind": "queen",
      "to": "c7",
      "command": "d8c7",
      "isCapture": false
    },
    {
      "side": "White",
      "pieceKind": "pawn",
      "to": "e5",
      "command": "e4e5",
      "isCapture": false
    },
    {
      "side": "Black",
      "pieceKind": "knight",
      "to": "e7",
      "command": "g8e7",
      "isCapture": false
    },
    {
      "side": "White",
      "pieceKind": "bishop",
      "to": "e2",
      "command": "f1e2",
      "isCapture": false
    },
    {
      "side": "Black",
      "pieceKind": "pawn",
      "to": "h6",
      "command": "h7h6",
      "isCapture": false
    },
    {
      "side": "White",
      "pieceKind": "bishop",
      "to": "d3",
      "command": "e2d3",
      "isCapture": false
    },
    {
      "side": "Black",
      "pieceKind": "pawn",
      "to": "a6",
      "command": "a7a6",
      "isCapture": false
    },
    {
      "side": "White",
      "pieceKind": "knight",
      "to": "e2",
      "command": "c3e2",
      "isCapture": false
    },
    {
      "side": "Black",
      "pieceKind": "pawn",
      "to": "c5",
      "command": "c6c5",
      "isCapture": false
    },
    {
      "side": "White",
      "pieceKind": "pawn",
      "to": "c5",
      "command": "d4c5",
      "isCapture": true,
      "capturedPieceKind": "pawn"
    },
    {
      "side": "Black",
      "pieceKind": "knight",
      "to": "d7",
      "command": "b8d7",
      "isCapture": false
    },
    {
      "side": "White",
      "pieceKind": "bishop",
      "to": "f4",
      "command": "c1f4",
      "isCapture": false
    },
    {
      "side": "Black",
      "pieceKind": "pawn",
      "to": "g5",
      "command": "g7g5",
      "isCapture": false
    },
    {
      "side": "White",
      "pieceKind": "bishop",
      "to": "g3",
      "command": "f4g3",
      "isCapture": false
    },
    {
      "side": "Black",
      "pieceKind": "knight",
      "to": "c5",
      "command": "d7c5",
      "isCapture": true,
      "capturedPieceKind": "pawn"
    },
    {
      "side": "White",
      "pieceKind": "pawn",
      "to": "h4",
      "command": "h2h4",
      "isCapture": false
    },
    {
      "side": "Black",
      "pieceKind": "rook",
      "to": "g8",
      "command": "h8g8",
      "isCapture": false
    },
    {
      "side": "White",
      "pieceKind": "pawn",
      "to": "g5",
      "command": "h4g5",
      "isCapture": true,
      "capturedPieceKind": "pawn"
    },
    {
      "side": "Black",
      "pieceKind": "pawn",
      "to": "g5",
      "command": "h6g5",
      "isCapture": true,
      "capturedPieceKind": "pawn"
    },
    {
      "side": "White",
      "pieceKind": "queen",
      "to": "d2",
      "command": "d1d2",
      "isCapture": false
    },
    {
      "side": "Black",
      "pieceKind": "bishop",
      "to": "d7",
      "command": "c8d7",
      "isCapture": false
    },
    {
      "side": "White",
      "pieceKind": "bishop",
      "to": "h7",
      "command": "d3h7",
      "isCapture": false
    },
    {
      "side": "Black",
      "pieceKind": "knight",
      "to": "e4",
      "command": "c5e4",
      "isCapture": false
    },
    {
      "side": "White",
      "pieceKind": "bishop",
      "to": "e4",
      "command": "h7e4",
      "isCapture": true,
      "capturedPieceKind": "knight"
    },
    {
      "side": "Black",
      "pieceKind": "pawn",
      "to": "e4",
      "command": "d5e4",
      "isCapture": true,
      "capturedPieceKind": "bishop"
    },
    {
      "side": "White",
      "pieceKind": "knight",
      "to": "d4",
      "command": "f3d4",
      "isCapture": false
    },
    {
      "side": "Black",
      "pieceKind": "knight",
      "to": "d5",
      "command": "e7d5",
      "isCapture": false
    },
    {
      "side": "White",
      "pieceKind": "pawn",
      "to": "a4",
      "command": "a2a4",
      "isCapture": false
    },
    {
      "side": "Black",
      "pieceKind": "queen",
      "to": "c4",
      "command": "c7c4",
      "isCapture": false
    },
    {
      "side": "White",
      "pieceKind": "pawn",
      "to": "c3",
      "command": "c2c3",
      "isCapture": false
    },
    {
      "side": "Black",
      "pieceKind": "bishop",
      "to": "a4",
      "command": "d7a4",
      "isCapture": true,
      "capturedPieceKind": "pawn"
    },
    {
      "side": "White",
      "pieceKind": "rook",
      "to": "h7",
      "command": "h1h7",
      "isCapture": false
    },
    {
      "side": "Black",
      "pieceKind": "pawn",
      "to": "b6",
      "command": "b7b6",
      "isCapture": false
    },
    {
      "side": "White",
      "pieceKind": "king",
      "to": "f1",
      "command": "e1f1",
      "isCapture": false
    },
    {
      "side": "Black",
      "pieceKind": "rook",
      "to": "b8",
      "command": "a8b8",
      "isCapture": false
    },
    {
      "side": "White",
      "pieceKind": "queen",
      "to": "c1",
      "command": "d2c1",
      "isCapture": false
    },
    {
      "side": "Black",
      "pieceKind": "bishop",
      "to": "d7",
      "command": "a4d7",
      "isCapture": false
    },
    {
      "side": "White",
      "pieceKind": "queen",
      "to": "d1",
      "command": "c1d1",
      "isCapture": false
    },
    {
      "side": "Black",
      "pieceKind": "rook",
      "to": "c8",
      "command": "b8c8",
      "isCapture": false
    },
    {
      "side": "White",
      "pieceKind": "queen",
      "to": "c2",
      "command": "d1c2",
      "isCapture": false
    },
    {
      "side": "Black",
      "pieceKind": "bishop",
      "to": "c6",
      "command": "d7c6",
      "isCapture": false
    },
    {
      "side": "White",
      "pieceKind": "queen",
      "to": "d1",
      "command": "c2d1",
      "isCapture": false
    },
    {
      "side": "Black",
      "pieceKind": "bishop",
      "to": "b7",
      "command": "c6b7",
      "isCapture": false
    },
    {
      "side": "White",
      "pieceKind": "king",
      "to": "g1",
      "command": "f1g1",
      "isCapture": false
    },
    {
      "side": "Black",
      "pieceKind": "rook",
      "to": "c7",
      "command": "c8c7",
      "isCapture": false
    },
    {
      "side": "White",
      "pieceKind": "queen",
      "to": "c2",
      "command": "d1c2",
      "isCapture": false
    },
    {
      "side": "Black",
      "pieceKind": "pawn",
      "to": "a5",
      "command": "a6a5",
      "isCapture": false
    },
    {
      "side": "White",
      "pieceKind": "bishop",
      "to": "h2",
      "command": "g3h2",
      "isCapture": false
    },
    {
      "side": "Black",
      "pieceKind": "queen",
      "to": "d3",
      "command": "c4d3",
      "isCapture": false
    },
    {
      "side": "White",
      "pieceKind": "queen",
      "to": "a4",
      "command": "c2a4",
      "isCapture": false
    },
    {
      "side": "Black",
      "pieceKind": "bishop",
      "to": "c6",
      "command": "b7c6",
      "isCapture": false
    },
    {
      "side": "White",
      "pieceKind": "knight",
      "to": "c6",
      "command": "d4c6",
      "isCapture": true,
      "capturedPieceKind": "bishop"
    },
    {
      "side": "Black",
      "pieceKind": "rook",
      "to": "d7",
      "command": "c7d7",
      "isCapture": false
    },
    {
      "side": "White",
      "pieceKind": "knight",
      "to": "b8",
      "command": "c6b8",
      "isCapture": false
    },
    {
      "side": "Black",
      "pieceKind": "pawn",
      "to": "b5",
      "command": "b6b5",
      "isCapture": false
    },
    {
      "side": "White",
      "pieceKind": "queen",
      "to": "a5",
      "command": "a4a5",
      "isCapture": true,
      "capturedPieceKind": "pawn"
    },
    {
      "side": "Black",
      "pieceKind": "knight",
      "to": "c3",
      "command": "d5c3",
      "isCapture": true,
      "capturedPieceKind": "pawn"
    },
    {
      "side": "White",
      "pieceKind": "knight",
      "to": "c3",
      "command": "e2c3",
      "isCapture": true,
      "capturedPieceKind": "knight"
    },
    {
      "side": "Black",
      "pieceKind": "pawn",
      "to": "e3",
      "command": "e4e3",
      "isCapture": false
    },
    {
      "side": "White",
      "pieceKind": "pawn",
      "to": "f3",
      "command": "f2f3",
      "isCapture": false
    },
    {
      "side": "Black",
      "pieceKind": "pawn",
      "to": "e2",
      "command": "e3e2",
      "isCapture": false
    },
    {
      "side": "White",
      "pieceKind": "king",
      "to": "h1",
      "command": "g1h1",
      "isCapture": false
    },
    {
      "side": "Black",
      "pieceKind": "bishop",
      "to": "e7",
      "command": "f8e7",
      "isCapture": false
    },
    {
      "side": "White",
      "pieceKind": "knight",
      "to": "d7",
      "command": "b8d7",
      "isCapture": true,
      "capturedPieceKind": "rook"
    },
    {
      "side": "Black",
      "pieceKind": "queen",
      "to": "d7",
      "command": "d3d7",
      "isCapture": true,
      "capturedPieceKind": "knight"
    },
    {
      "side": "White",
      "pieceKind": "rook",
      "to": "e1",
      "command": "a1e1",
      "isCapture": false
    },
    {
      "side": "Black",
      "pieceKind": "pawn",
      "to": "b4",
      "command": "b5b4",
      "isCapture": false
    },
    {
      "side": "White",
      "pieceKind": "queen",
      "to": "a8",
      "command": "a5a8",
      "isCapture": false
    },
    {
      "side": "Black",
      "pieceKind": "bishop",
      "to": "d8",
      "command": "e7d8",
      "isCapture": false
    },
    {
      "side": "White",
      "pieceKind": "knight",
      "to": "e4",
      "command": "c3e4",
      "isCapture": false
    },
    {
      "side": "Black",
      "pieceKind": "queen",
      "to": "c7",
      "command": "d7c7",
      "isCapture": false
    },
    {
      "side": "White",
      "pieceKind": "knight",
      "to": "d6",
      "command": "e4d6",
      "isCapture": false
    },
    {
      "side": "Black",
      "pieceKind": "queen",
      "to": "d6",
      "command": "c7d6",
      "isCapture": true,
      "capturedPieceKind": "knight"
    },
    {
      "side": "White",
      "pieceKind": "pawn",
      "to": "d6",
      "command": "e5d6",
      "isCapture": true,
      "capturedPieceKind": "queen"
    },
    {
      "side": "Black",
      "pieceKind": "pawn",
      "to": "e5",
      "command": "e6e5",
      "isCapture": false
    },
    {
      "side": "White",
      "pieceKind": "queen",
      "to": "b7",
      "command": "a8b7",
      "isCapture": false
    },
    {
      "side": "Black",
      "pieceKind": "rook",
      "to": "g7",
      "command": "g8g7",
      "isCapture": false
    },
    {
      "side": "White",
      "pieceKind": "rook",
      "to": "h8",
      "command": "h7h8",
      "isCapture": false
    },
    {
      "side": "Black",
      "pieceKind": "rook",
      "to": "g8",
      "command": "g7g8",
      "isCapture": false
    },
    {
      "side": "White",
      "pieceKind": "rook",
      "to": "h7",
      "command": "h8h7",
      "isCapture": false
    },
    {
      "side": "Black",
      "pieceKind": "bishop",
      "to": "c7",
      "command": "d8c7",
      "isCapture": false
    },
    {
      "side": "White",
      "pieceKind": "pawn",
      "to": "c7",
      "command": "d6c7",
      "isCapture": true,
      "capturedPieceKind": "bishop"
    },
    {
      "side": "Black",
      "pieceKind": "pawn",
      "to": "b3",
      "command": "b4b3",
      "isCapture": false
    },
    {
      "side": "White",
      "pieceKind": "queen",
      "to": "c8",
      "command": "c7c8q",
      "isCapture": false
    }
  ],
  "mode": "ai_vs_ai",
  "move_count": 91,
  "profile": "intermediate",
  "result": "white_win",
  "winner": "white"
}